bingx/__init__.py
bingx/api.py
py_bingx_d-0.2.dist-info/LICENSE
py_bingx_d-0.2.dist-info/METADATA
py_bingx_d-0.2.dist-info/WHEEL
py_bingx_d-0.2.dist-info/top_level.txt
py_bingx_d-0.2.dist-info/RECORD
