Metadata-Version: 2.1
Name: py-bingx-d
Version: 0.2
Summary: BingX REST API Python implementation Pluse
Home-page: https://github.com/rikhtehgaran/py-bingx-d
Author: Danial Rikhteh Garan
Author-email: 
License: MIT
Keywords: bingx api cryptocurrency trading btc eth rest exchange
Classifier: Intended Audience :: Developers
Classifier: License :: OSI Approved :: MIT License
Classifier: Operating System :: OS Independent
Classifier: Programming Language :: Python :: 3
Classifier: Programming Language :: Python :: 3.8
Classifier: Programming Language :: Python :: 3.9
Classifier: Programming Language :: Python :: 3.10
Classifier: Programming Language :: Python
Classifier: Topic :: Software Development :: Libraries :: Python Modules
License-File: LICENSE
Requires-Dist: requests
